{
    "/js/app.js": "/js/app.js",
    "/css/app.css": "/css/app.css",
    "/0.9165a2b58313a49f47e7.hot-update.js": "/0.9165a2b58313a49f47e7.hot-update.js",
    "/0.6aafe72273728a5d97b3.hot-update.js": "/0.6aafe72273728a5d97b3.hot-update.js",
    "/0.b8f84d8cbca84f4915b5.hot-update.js": "/0.b8f84d8cbca84f4915b5.hot-update.js",
    "/0.206c1e36056bc2e37a2a.hot-update.js": "/0.206c1e36056bc2e37a2a.hot-update.js",
    "/0.10d68708dad8b1d976c0.hot-update.js": "/0.10d68708dad8b1d976c0.hot-update.js",
    "/0.25e3236564f283d27c53.hot-update.js": "/0.25e3236564f283d27c53.hot-update.js",
    "/0.31ac7f53afd4f3f2776f.hot-update.js": "/0.31ac7f53afd4f3f2776f.hot-update.js",
    "/0.21d0b83fe681e4a259aa.hot-update.js": "/0.21d0b83fe681e4a259aa.hot-update.js",
    "/0.e15f7ad6319873611e64.hot-update.js": "/0.e15f7ad6319873611e64.hot-update.js",
    "/0.dd4ff2c17b8ae74ba8fc.hot-update.js": "/0.dd4ff2c17b8ae74ba8fc.hot-update.js",
    "/0.57ffb41c406e27ac8fba.hot-update.js": "/0.57ffb41c406e27ac8fba.hot-update.js",
    "/0.550d07542601f47f0e82.hot-update.js": "/0.550d07542601f47f0e82.hot-update.js",
    "/0.da790ebe3d4b3d0bb90d.hot-update.js": "/0.da790ebe3d4b3d0bb90d.hot-update.js",
    "/0.b72e45fbcbc465e53d8b.hot-update.js": "/0.b72e45fbcbc465e53d8b.hot-update.js",
    "/0.6ca5579dee5f5fdda861.hot-update.js": "/0.6ca5579dee5f5fdda861.hot-update.js",
    "/0.77e96955cfb73b6956ae.hot-update.js": "/0.77e96955cfb73b6956ae.hot-update.js",
    "/0.ea4a6a46875abfb1be6a.hot-update.js": "/0.ea4a6a46875abfb1be6a.hot-update.js",
    "/0.0cdb4122b81db2608e32.hot-update.js": "/0.0cdb4122b81db2608e32.hot-update.js",
    "/0.394ae1ceec5b49e33e60.hot-update.js": "/0.394ae1ceec5b49e33e60.hot-update.js",
    "/0.7d8b7ac6fcdbabc47281.hot-update.js": "/0.7d8b7ac6fcdbabc47281.hot-update.js",
    "/0.7dde0de5d02763b430ea.hot-update.js": "/0.7dde0de5d02763b430ea.hot-update.js",
    "/0.c2af498f8a25576943e5.hot-update.js": "/0.c2af498f8a25576943e5.hot-update.js",
    "/0.8a67a5c2ea477e90eb34.hot-update.js": "/0.8a67a5c2ea477e90eb34.hot-update.js",
    "/0.6783caa7dac83e533c0e.hot-update.js": "/0.6783caa7dac83e533c0e.hot-update.js",
    "/0.c822c21143558c4f67e3.hot-update.js": "/0.c822c21143558c4f67e3.hot-update.js",
    "/0.7952ad984f9ef9a3c852.hot-update.js": "/0.7952ad984f9ef9a3c852.hot-update.js",
    "/0.a28f990f1ff5f6e25824.hot-update.js": "/0.a28f990f1ff5f6e25824.hot-update.js",
    "/0.a6bfbc480859831531d1.hot-update.js": "/0.a6bfbc480859831531d1.hot-update.js",
    "/0.96280cf2347011a01b83.hot-update.js": "/0.96280cf2347011a01b83.hot-update.js",
    "/0.14d76f54dd3927978780.hot-update.js": "/0.14d76f54dd3927978780.hot-update.js",
    "/0.09953dcf76a8f6563ee9.hot-update.js": "/0.09953dcf76a8f6563ee9.hot-update.js",
    "/0.7e9c3b146e32c9282bd8.hot-update.js": "/0.7e9c3b146e32c9282bd8.hot-update.js",
    "/0.378814b01c7d66f0f0dd.hot-update.js": "/0.378814b01c7d66f0f0dd.hot-update.js",
    "/0.55698dc0ba0a9b5b513e.hot-update.js": "/0.55698dc0ba0a9b5b513e.hot-update.js",
    "/0.ff29cf87b693171cb08f.hot-update.js": "/0.ff29cf87b693171cb08f.hot-update.js",
    "/0.2fd27e771f45476df9ac.hot-update.js": "/0.2fd27e771f45476df9ac.hot-update.js",
    "/0.4e1d25e1742944afe1c6.hot-update.js": "/0.4e1d25e1742944afe1c6.hot-update.js",
    "/0.62979d4e8417c30f52e7.hot-update.js": "/0.62979d4e8417c30f52e7.hot-update.js",
    "/0.f1a26530a1ac0a18f5d7.hot-update.js": "/0.f1a26530a1ac0a18f5d7.hot-update.js",
    "/0.ca9552a70eca017525e4.hot-update.js": "/0.ca9552a70eca017525e4.hot-update.js",
    "/0.8975c402ac7284ea6834.hot-update.js": "/0.8975c402ac7284ea6834.hot-update.js",
    "/0.e4a9276160d95118858a.hot-update.js": "/0.e4a9276160d95118858a.hot-update.js",
    "/0.da15cc2be3cf28a23ee5.hot-update.js": "/0.da15cc2be3cf28a23ee5.hot-update.js",
    "/0.c25ff62178d904096418.hot-update.js": "/0.c25ff62178d904096418.hot-update.js",
    "/0.c75fb9417ff11eef10ed.hot-update.js": "/0.c75fb9417ff11eef10ed.hot-update.js",
    "/0.d62a9ae28c1ff61949e3.hot-update.js": "/0.d62a9ae28c1ff61949e3.hot-update.js",
    "/0.afd053bc8dc8d00539b2.hot-update.js": "/0.afd053bc8dc8d00539b2.hot-update.js",
    "/0.9b0b5b2049684ac86932.hot-update.js": "/0.9b0b5b2049684ac86932.hot-update.js",
    "/0.1c02fd9abe5cbeff4300.hot-update.js": "/0.1c02fd9abe5cbeff4300.hot-update.js",
    "/0.44e4b7f2219e043c5ccf.hot-update.js": "/0.44e4b7f2219e043c5ccf.hot-update.js",
    "/0.163f9d9eeffc2727812a.hot-update.js": "/0.163f9d9eeffc2727812a.hot-update.js",
    "/0.05c2564f56355e99d8e0.hot-update.js": "/0.05c2564f56355e99d8e0.hot-update.js",
    "/0.749f69f310977fac5cec.hot-update.js": "/0.749f69f310977fac5cec.hot-update.js",
    "/0.534e4ede982b580c9767.hot-update.js": "/0.534e4ede982b580c9767.hot-update.js",
    "/0.f30c345ac5396b5d5be2.hot-update.js": "/0.f30c345ac5396b5d5be2.hot-update.js",
    "/0.1b53a2b460be403a2db9.hot-update.js": "/0.1b53a2b460be403a2db9.hot-update.js",
    "/0.1c200af39dd1ec67f301.hot-update.js": "/0.1c200af39dd1ec67f301.hot-update.js",
    "/0.038b1099db1488a9eb09.hot-update.js": "/0.038b1099db1488a9eb09.hot-update.js",
    "/0.1ca6e181056db8c57da3.hot-update.js": "/0.1ca6e181056db8c57da3.hot-update.js",
    "/0.911c77b7c712eafa61f7.hot-update.js": "/0.911c77b7c712eafa61f7.hot-update.js",
    "/0.96b2feaf6b9415314171.hot-update.js": "/0.96b2feaf6b9415314171.hot-update.js",
    "/0.e72e57b296b94d66e856.hot-update.js": "/0.e72e57b296b94d66e856.hot-update.js",
    "/0.26013dc87c0a1d2389bb.hot-update.js": "/0.26013dc87c0a1d2389bb.hot-update.js",
    "/0.3c5a0644cb74d27f12a1.hot-update.js": "/0.3c5a0644cb74d27f12a1.hot-update.js",
    "/0.f439c4aa480574a7a71e.hot-update.js": "/0.f439c4aa480574a7a71e.hot-update.js",
    "/0.1d6458779a612e87a99a.hot-update.js": "/0.1d6458779a612e87a99a.hot-update.js",
    "/0.97b89e8a71eea0e77f37.hot-update.js": "/0.97b89e8a71eea0e77f37.hot-update.js",
    "/0.f9700d384a752008cb98.hot-update.js": "/0.f9700d384a752008cb98.hot-update.js",
    "/0.8429434da1f2b13f6e23.hot-update.js": "/0.8429434da1f2b13f6e23.hot-update.js",
    "/0.159bdc9850ccb9817cd2.hot-update.js": "/0.159bdc9850ccb9817cd2.hot-update.js",
    "/0.5e5378f02ab4087fd36b.hot-update.js": "/0.5e5378f02ab4087fd36b.hot-update.js",
    "/0.321e75f08cabda7b3da1.hot-update.js": "/0.321e75f08cabda7b3da1.hot-update.js",
    "/0.9e2fa0c330351e2e3ab7.hot-update.js": "/0.9e2fa0c330351e2e3ab7.hot-update.js",
    "/0.6a3a394c091f42456730.hot-update.js": "/0.6a3a394c091f42456730.hot-update.js",
    "/0.160e4020edcce94cd42b.hot-update.js": "/0.160e4020edcce94cd42b.hot-update.js",
    "/0.abb3f5835b5f41f95835.hot-update.js": "/0.abb3f5835b5f41f95835.hot-update.js",
    "/0.571d5d56b9e52f6d25c1.hot-update.js": "/0.571d5d56b9e52f6d25c1.hot-update.js",
    "/0.81354134015a84637b7e.hot-update.js": "/0.81354134015a84637b7e.hot-update.js",
    "/0.d33137ff550db7c05fb9.hot-update.js": "/0.d33137ff550db7c05fb9.hot-update.js",
    "/0.3358ef81f217a1de10bd.hot-update.js": "/0.3358ef81f217a1de10bd.hot-update.js",
    "/0.86fd1c6b722323f51fe6.hot-update.js": "/0.86fd1c6b722323f51fe6.hot-update.js",
    "/0.b3898b83fd2a6e7fe9d0.hot-update.js": "/0.b3898b83fd2a6e7fe9d0.hot-update.js",
    "/0.193883b3af6b02836f62.hot-update.js": "/0.193883b3af6b02836f62.hot-update.js",
    "/0.9664435099bd7dc545a1.hot-update.js": "/0.9664435099bd7dc545a1.hot-update.js",
    "/0.f602ecdd7d9869f349b9.hot-update.js": "/0.f602ecdd7d9869f349b9.hot-update.js",
    "/0.691f714e50370d7ba823.hot-update.js": "/0.691f714e50370d7ba823.hot-update.js",
    "/0.564ef08ebd142d5a726d.hot-update.js": "/0.564ef08ebd142d5a726d.hot-update.js",
    "/0.f77cf58b5b9d1a2da1ec.hot-update.js": "/0.f77cf58b5b9d1a2da1ec.hot-update.js",
    "/0.272a6e2c6d549fd5b43b.hot-update.js": "/0.272a6e2c6d549fd5b43b.hot-update.js",
    "/0.98be9cb13ac3703e6d7f.hot-update.js": "/0.98be9cb13ac3703e6d7f.hot-update.js",
    "/0.9fb63176443c879ff3f7.hot-update.js": "/0.9fb63176443c879ff3f7.hot-update.js",
    "/0.f5d35a9162a84d4614e4.hot-update.js": "/0.f5d35a9162a84d4614e4.hot-update.js",
    "/0.dd009a8fd04292c5037b.hot-update.js": "/0.dd009a8fd04292c5037b.hot-update.js",
    "/0.e94a40d8ee89b4f350c5.hot-update.js": "/0.e94a40d8ee89b4f350c5.hot-update.js",
    "/0.c0ac4d57a1a6d38896e2.hot-update.js": "/0.c0ac4d57a1a6d38896e2.hot-update.js",
    "/0.13bf221a81a87053fe05.hot-update.js": "/0.13bf221a81a87053fe05.hot-update.js",
    "/0.e4aa9c86054e80cf1ce9.hot-update.js": "/0.e4aa9c86054e80cf1ce9.hot-update.js",
    "/0.dfda46ddd7f228db2456.hot-update.js": "/0.dfda46ddd7f228db2456.hot-update.js",
    "/0.a12b3de590a5bf812548.hot-update.js": "/0.a12b3de590a5bf812548.hot-update.js",
    "/0.ed11d779e0c957217512.hot-update.js": "/0.ed11d779e0c957217512.hot-update.js",
    "/0.4323553b06e65f6298f5.hot-update.js": "/0.4323553b06e65f6298f5.hot-update.js",
    "/0.10e52e06be89e0e33e7f.hot-update.js": "/0.10e52e06be89e0e33e7f.hot-update.js",
    "/0.4f72e467be59173ed1c4.hot-update.js": "/0.4f72e467be59173ed1c4.hot-update.js",
    "/0.7af248f90076d86c0131.hot-update.js": "/0.7af248f90076d86c0131.hot-update.js",
    "/0.8bfc5c0c8e8c2a312758.hot-update.js": "/0.8bfc5c0c8e8c2a312758.hot-update.js",
    "/0.a84a66b98c9474bca9ad.hot-update.js": "/0.a84a66b98c9474bca9ad.hot-update.js",
    "/0.9dfc3a5e50b157d85695.hot-update.js": "/0.9dfc3a5e50b157d85695.hot-update.js",
    "/0.9eb2266dcb1000144753.hot-update.js": "/0.9eb2266dcb1000144753.hot-update.js",
    "/0.fb62ebf9dd74b2e61586.hot-update.js": "/0.fb62ebf9dd74b2e61586.hot-update.js",
    "/0.d64920d85b871d9bb139.hot-update.js": "/0.d64920d85b871d9bb139.hot-update.js",
    "/0.5b24a072327e8db7f13d.hot-update.js": "/0.5b24a072327e8db7f13d.hot-update.js",
    "/0.87a258f7daca769bd362.hot-update.js": "/0.87a258f7daca769bd362.hot-update.js",
    "/0.b30d9dbf3e2cbfb9bee7.hot-update.js": "/0.b30d9dbf3e2cbfb9bee7.hot-update.js",
    "/0.871ebd97a5d9f0b382d0.hot-update.js": "/0.871ebd97a5d9f0b382d0.hot-update.js",
    "/0.8e730045c36e0589f89a.hot-update.js": "/0.8e730045c36e0589f89a.hot-update.js",
    "/0.cbc6c74845154b82549b.hot-update.js": "/0.cbc6c74845154b82549b.hot-update.js",
    "/0.b2726e944a65f3fb00ba.hot-update.js": "/0.b2726e944a65f3fb00ba.hot-update.js",
    "/0.ce2bbe812d93ab395c4b.hot-update.js": "/0.ce2bbe812d93ab395c4b.hot-update.js",
    "/0.b01d6cd87012a87664e1.hot-update.js": "/0.b01d6cd87012a87664e1.hot-update.js",
    "/0.a15c31c94c1a23725187.hot-update.js": "/0.a15c31c94c1a23725187.hot-update.js",
    "/0.9d7bc15beab926841db6.hot-update.js": "/0.9d7bc15beab926841db6.hot-update.js",
    "/0.af9228f2ad2b2a7dadea.hot-update.js": "/0.af9228f2ad2b2a7dadea.hot-update.js",
    "/0.7410fff244cf9c13d85f.hot-update.js": "/0.7410fff244cf9c13d85f.hot-update.js",
    "/0.99daf10e6cb7814eda16.hot-update.js": "/0.99daf10e6cb7814eda16.hot-update.js",
    "/0.0e9cb471d53157964e88.hot-update.js": "/0.0e9cb471d53157964e88.hot-update.js",
    "/0.a80baf2068e56f511a01.hot-update.js": "/0.a80baf2068e56f511a01.hot-update.js",
    "/0.863ae20c088384a5c84e.hot-update.js": "/0.863ae20c088384a5c84e.hot-update.js",
    "/0.689a12f6bfeabf75cf19.hot-update.js": "/0.689a12f6bfeabf75cf19.hot-update.js",
    "/0.e82ac7de1ea53438194f.hot-update.js": "/0.e82ac7de1ea53438194f.hot-update.js",
    "/0.b47ea1401b9e1945eb90.hot-update.js": "/0.b47ea1401b9e1945eb90.hot-update.js",
    "/0.5bc444de0728b5045ec3.hot-update.js": "/0.5bc444de0728b5045ec3.hot-update.js",
    "/0.4d66148be14f82a06ff7.hot-update.js": "/0.4d66148be14f82a06ff7.hot-update.js",
    "/0.7b0bda8e79f34ca9b3b2.hot-update.js": "/0.7b0bda8e79f34ca9b3b2.hot-update.js",
    "/0.3dfedc9c7a2648cf4095.hot-update.js": "/0.3dfedc9c7a2648cf4095.hot-update.js",
    "/0.83bce437615842c99138.hot-update.js": "/0.83bce437615842c99138.hot-update.js",
    "/0.c1ebb33a64037688c8af.hot-update.js": "/0.c1ebb33a64037688c8af.hot-update.js",
    "/0.56688b6427b5165df997.hot-update.js": "/0.56688b6427b5165df997.hot-update.js",
    "/0.00f9fa74bdb9ab6ff61f.hot-update.js": "/0.00f9fa74bdb9ab6ff61f.hot-update.js",
    "/0.60d147d34b2bad24ac10.hot-update.js": "/0.60d147d34b2bad24ac10.hot-update.js",
    "/0.4b43a35738c5240fb0aa.hot-update.js": "/0.4b43a35738c5240fb0aa.hot-update.js",
    "/0.277994cf4b0a171b8c83.hot-update.js": "/0.277994cf4b0a171b8c83.hot-update.js",
    "/0.89615d8070160fd72d96.hot-update.js": "/0.89615d8070160fd72d96.hot-update.js",
    "/0.c7c420d81da4d56dbe07.hot-update.js": "/0.c7c420d81da4d56dbe07.hot-update.js",
    "/0.898f99af46bb7732d8d2.hot-update.js": "/0.898f99af46bb7732d8d2.hot-update.js",
    "/0.7307e10cc248e77926fb.hot-update.js": "/0.7307e10cc248e77926fb.hot-update.js",
    "/0.6f3474e8225616b17052.hot-update.js": "/0.6f3474e8225616b17052.hot-update.js",
    "/0.3667b33e2099c250a798.hot-update.js": "/0.3667b33e2099c250a798.hot-update.js",
    "/0.67a76f8ebe8c6b88aaad.hot-update.js": "/0.67a76f8ebe8c6b88aaad.hot-update.js",
    "/0.576c95fc6e2b68081489.hot-update.js": "/0.576c95fc6e2b68081489.hot-update.js",
    "/0.bf26e8aa2739d93eedea.hot-update.js": "/0.bf26e8aa2739d93eedea.hot-update.js",
    "/0.a9aa760baab3be1eaacf.hot-update.js": "/0.a9aa760baab3be1eaacf.hot-update.js",
    "/0.254d70ecc524a95ab0e9.hot-update.js": "/0.254d70ecc524a95ab0e9.hot-update.js",
    "/0.28818c45c1b0abafbc41.hot-update.js": "/0.28818c45c1b0abafbc41.hot-update.js",
    "/0.2da44c74b249f2593e2a.hot-update.js": "/0.2da44c74b249f2593e2a.hot-update.js",
    "/0.5b5a323281f4000148ef.hot-update.js": "/0.5b5a323281f4000148ef.hot-update.js",
    "/0.05e4c9e605376ec70368.hot-update.js": "/0.05e4c9e605376ec70368.hot-update.js",
    "/0.05b7397f9aab26115d6d.hot-update.js": "/0.05b7397f9aab26115d6d.hot-update.js",
    "/0.0bedc5db92329c0398b5.hot-update.js": "/0.0bedc5db92329c0398b5.hot-update.js",
    "/0.c99fa87cce6ca58eef0e.hot-update.js": "/0.c99fa87cce6ca58eef0e.hot-update.js",
    "/0.42579fa5387d08da0914.hot-update.js": "/0.42579fa5387d08da0914.hot-update.js",
    "/0.21ab4d1dec60bc561106.hot-update.js": "/0.21ab4d1dec60bc561106.hot-update.js",
    "/0.5f42c198bcb73aa0c5bf.hot-update.js": "/0.5f42c198bcb73aa0c5bf.hot-update.js",
    "/0.7692ceffbaf0385c13b5.hot-update.js": "/0.7692ceffbaf0385c13b5.hot-update.js",
    "/0.720bba2b6a2e7706ffab.hot-update.js": "/0.720bba2b6a2e7706ffab.hot-update.js",
    "/0.0a5b3ad6e9368587e4c0.hot-update.js": "/0.0a5b3ad6e9368587e4c0.hot-update.js",
    "/0.3b9e3a6020a92d716a02.hot-update.js": "/0.3b9e3a6020a92d716a02.hot-update.js",
    "/0.3b28a4aa53964d6072ea.hot-update.js": "/0.3b28a4aa53964d6072ea.hot-update.js",
    "/0.4e844871933dacca6b27.hot-update.js": "/0.4e844871933dacca6b27.hot-update.js",
    "/0.cd745610d175d8018708.hot-update.js": "/0.cd745610d175d8018708.hot-update.js",
    "/0.bb725613315624aa26b5.hot-update.js": "/0.bb725613315624aa26b5.hot-update.js",
    "/0.b6e4f1c59cee40a55f32.hot-update.js": "/0.b6e4f1c59cee40a55f32.hot-update.js",
    "/0.d0ec9e6679d0b703f9a6.hot-update.js": "/0.d0ec9e6679d0b703f9a6.hot-update.js",
    "/0.0cc493c86c59f8950371.hot-update.js": "/0.0cc493c86c59f8950371.hot-update.js",
    "/0.35ac377c18de3ce9e966.hot-update.js": "/0.35ac377c18de3ce9e966.hot-update.js",
    "/0.c00ba0566364d811c357.hot-update.js": "/0.c00ba0566364d811c357.hot-update.js",
    "/0.683967edc997e767c8ee.hot-update.js": "/0.683967edc997e767c8ee.hot-update.js",
    "/0.7705f92ff52ae2fc0e8f.hot-update.js": "/0.7705f92ff52ae2fc0e8f.hot-update.js",
    "/0.3e0ab4cd352061e931e6.hot-update.js": "/0.3e0ab4cd352061e931e6.hot-update.js",
    "/0.adaeb82ff9e01d05492b.hot-update.js": "/0.adaeb82ff9e01d05492b.hot-update.js",
    "/0.1fa8b2ebcf667c9367ca.hot-update.js": "/0.1fa8b2ebcf667c9367ca.hot-update.js",
    "/0.0200dcd951238c786b33.hot-update.js": "/0.0200dcd951238c786b33.hot-update.js",
    "/0.250a9f4af8d3ad10c01a.hot-update.js": "/0.250a9f4af8d3ad10c01a.hot-update.js",
    "/0.602de79469f7e06ea1a6.hot-update.js": "/0.602de79469f7e06ea1a6.hot-update.js",
    "/0.45002ed2b226a07984b0.hot-update.js": "/0.45002ed2b226a07984b0.hot-update.js",
    "/0.5d3ad56a0287ef767f62.hot-update.js": "/0.5d3ad56a0287ef767f62.hot-update.js",
    "/0.b37df896d4fd7410f5a7.hot-update.js": "/0.b37df896d4fd7410f5a7.hot-update.js",
    "/0.a7dc1114f4e1ca3cea04.hot-update.js": "/0.a7dc1114f4e1ca3cea04.hot-update.js",
    "/0.105e273efbf3521bb717.hot-update.js": "/0.105e273efbf3521bb717.hot-update.js",
    "/0.7ceba4cf960eb75af951.hot-update.js": "/0.7ceba4cf960eb75af951.hot-update.js",
    "/0.96b41ce27b27e0a25104.hot-update.js": "/0.96b41ce27b27e0a25104.hot-update.js",
    "/0.66b7002c5806d262e184.hot-update.js": "/0.66b7002c5806d262e184.hot-update.js",
    "/0.12544258ec5b0be54187.hot-update.js": "/0.12544258ec5b0be54187.hot-update.js",
    "/0.379d75d146af8f5579ec.hot-update.js": "/0.379d75d146af8f5579ec.hot-update.js",
    "/0.56944efa2b977153f263.hot-update.js": "/0.56944efa2b977153f263.hot-update.js",
    "/0.c8c125bdb0d9678c3fed.hot-update.js": "/0.c8c125bdb0d9678c3fed.hot-update.js",
    "/0.809a30c2d96b2a3b6af5.hot-update.js": "/0.809a30c2d96b2a3b6af5.hot-update.js",
    "/0.95ff4eada15bebf2fea8.hot-update.js": "/0.95ff4eada15bebf2fea8.hot-update.js",
    "/0.7724c0351c45905a287a.hot-update.js": "/0.7724c0351c45905a287a.hot-update.js",
    "/0.cff09b9fd4d7966c8277.hot-update.js": "/0.cff09b9fd4d7966c8277.hot-update.js",
    "/0.e44c941145aed19adfbf.hot-update.js": "/0.e44c941145aed19adfbf.hot-update.js",
    "/0.fa3a4b61798415141429.hot-update.js": "/0.fa3a4b61798415141429.hot-update.js",
    "/0.76d4d47b35431e037cbb.hot-update.js": "/0.76d4d47b35431e037cbb.hot-update.js",
    "/0.295427417263a3daac6c.hot-update.js": "/0.295427417263a3daac6c.hot-update.js",
    "/0.1fd3b1fe5fa073c65fb6.hot-update.js": "/0.1fd3b1fe5fa073c65fb6.hot-update.js",
    "/0.b04fad30d2cfa8470bfb.hot-update.js": "/0.b04fad30d2cfa8470bfb.hot-update.js",
    "/0.e93fbda120a9c2ef69fd.hot-update.js": "/0.e93fbda120a9c2ef69fd.hot-update.js",
    "/0.52dbab74944f32578d3f.hot-update.js": "/0.52dbab74944f32578d3f.hot-update.js",
    "/0.6645df1bacf1fb630c2c.hot-update.js": "/0.6645df1bacf1fb630c2c.hot-update.js",
    "/0.98e6722fed010885a8c9.hot-update.js": "/0.98e6722fed010885a8c9.hot-update.js",
    "/0.76e53d8c1008229f2704.hot-update.js": "/0.76e53d8c1008229f2704.hot-update.js",
    "/0.dccfd3a99be316ec82de.hot-update.js": "/0.dccfd3a99be316ec82de.hot-update.js",
    "/0.4476b8526b55ab9c0c96.hot-update.js": "/0.4476b8526b55ab9c0c96.hot-update.js",
    "/0.73998bca054316d87022.hot-update.js": "/0.73998bca054316d87022.hot-update.js",
    "/0.82787459992ee5c37c60.hot-update.js": "/0.82787459992ee5c37c60.hot-update.js",
    "/0.e0fc10f32a22623aa5d3.hot-update.js": "/0.e0fc10f32a22623aa5d3.hot-update.js",
    "/0.956e93e725eb4913ee89.hot-update.js": "/0.956e93e725eb4913ee89.hot-update.js",
    "/0.784a0a0261b216969a53.hot-update.js": "/0.784a0a0261b216969a53.hot-update.js",
    "/0.05f5641d8993fe4dc8b1.hot-update.js": "/0.05f5641d8993fe4dc8b1.hot-update.js",
    "/0.d770eb1693c19453227f.hot-update.js": "/0.d770eb1693c19453227f.hot-update.js",
    "/0.c9207a024e64cb55eece.hot-update.js": "/0.c9207a024e64cb55eece.hot-update.js",
    "/0.058b8b6727cbaa22a3f9.hot-update.js": "/0.058b8b6727cbaa22a3f9.hot-update.js",
    "/0.fbdc1f039b2ebc3e96b6.hot-update.js": "/0.fbdc1f039b2ebc3e96b6.hot-update.js",
    "/0.6e2a8912e650d270e922.hot-update.js": "/0.6e2a8912e650d270e922.hot-update.js",
    "/0.70408f100b54895d765f.hot-update.js": "/0.70408f100b54895d765f.hot-update.js",
    "/0.6a7a59a149ddb5258512.hot-update.js": "/0.6a7a59a149ddb5258512.hot-update.js",
    "/0.ac49b26decf893d1d87a.hot-update.js": "/0.ac49b26decf893d1d87a.hot-update.js",
    "/0.040330444161cf63e2a9.hot-update.js": "/0.040330444161cf63e2a9.hot-update.js",
    "/0.be5eb563ca326c16cc49.hot-update.js": "/0.be5eb563ca326c16cc49.hot-update.js",
    "/0.f684796d9080dffe501e.hot-update.js": "/0.f684796d9080dffe501e.hot-update.js",
    "/0.fefb4c7f3f7a8bc56980.hot-update.js": "/0.fefb4c7f3f7a8bc56980.hot-update.js",
    "/0.321a8c9e551f8c86d2b1.hot-update.js": "/0.321a8c9e551f8c86d2b1.hot-update.js",
    "/0.89bcc727bee6f789b733.hot-update.js": "/0.89bcc727bee6f789b733.hot-update.js",
    "/0.7c33851ba4fae5489f8d.hot-update.js": "/0.7c33851ba4fae5489f8d.hot-update.js",
    "/0.7d643982474013b59b65.hot-update.js": "/0.7d643982474013b59b65.hot-update.js",
    "/0.efc645905175a69af46d.hot-update.js": "/0.efc645905175a69af46d.hot-update.js",
    "/0.4fffc9549da6fad59a38.hot-update.js": "/0.4fffc9549da6fad59a38.hot-update.js",
    "/0.1c844763196137256ddc.hot-update.js": "/0.1c844763196137256ddc.hot-update.js",
    "/0.310dec6bb2f9b5c8c287.hot-update.js": "/0.310dec6bb2f9b5c8c287.hot-update.js",
    "/0.62eeec6f584db2ff02c7.hot-update.js": "/0.62eeec6f584db2ff02c7.hot-update.js",
    "/0.654e201f1970d66b8a5b.hot-update.js": "/0.654e201f1970d66b8a5b.hot-update.js",
    "/0.fa646820dcf4dec59532.hot-update.js": "/0.fa646820dcf4dec59532.hot-update.js",
    "/0.f05f560a057b4d5292ae.hot-update.js": "/0.f05f560a057b4d5292ae.hot-update.js",
    "/0.7f0f5a26d17498f18995.hot-update.js": "/0.7f0f5a26d17498f18995.hot-update.js",
    "/0.e64ee83aeefa5cb26568.hot-update.js": "/0.e64ee83aeefa5cb26568.hot-update.js",
    "/0.bcbbe266ee2cee2d44cf.hot-update.js": "/0.bcbbe266ee2cee2d44cf.hot-update.js",
    "/0.d10beb5837d8792de33d.hot-update.js": "/0.d10beb5837d8792de33d.hot-update.js",
    "/0.c82914b39a2474909463.hot-update.js": "/0.c82914b39a2474909463.hot-update.js",
    "/0.e0f6c70857e3f174e3a8.hot-update.js": "/0.e0f6c70857e3f174e3a8.hot-update.js",
    "/0.571de9745408fdf55ded.hot-update.js": "/0.571de9745408fdf55ded.hot-update.js",
    "/0.d2d580261a87fd07ea3c.hot-update.js": "/0.d2d580261a87fd07ea3c.hot-update.js",
    "/0.89408af52aebda8a8beb.hot-update.js": "/0.89408af52aebda8a8beb.hot-update.js",
    "/0.9d62b2c7ee717a2a0155.hot-update.js": "/0.9d62b2c7ee717a2a0155.hot-update.js",
    "/0.ac502511a0283657fc89.hot-update.js": "/0.ac502511a0283657fc89.hot-update.js",
    "/0.7beff8502cc51c7de7b5.hot-update.js": "/0.7beff8502cc51c7de7b5.hot-update.js",
    "/0.ff83e4939c5da24599ad.hot-update.js": "/0.ff83e4939c5da24599ad.hot-update.js",
    "/0.151768331830a5309a82.hot-update.js": "/0.151768331830a5309a82.hot-update.js",
    "/0.fc69543ddcb44cf7b435.hot-update.js": "/0.fc69543ddcb44cf7b435.hot-update.js",
    "/0.ca70d3a5e3480d855c82.hot-update.js": "/0.ca70d3a5e3480d855c82.hot-update.js",
    "/0.126066ffd8a3d2875543.hot-update.js": "/0.126066ffd8a3d2875543.hot-update.js",
    "/0.ecbb1ba3182dfba2ecc9.hot-update.js": "/0.ecbb1ba3182dfba2ecc9.hot-update.js",
    "/0.fb5311cd6bceff9187a6.hot-update.js": "/0.fb5311cd6bceff9187a6.hot-update.js",
    "/0.31900f2b254c0a965025.hot-update.js": "/0.31900f2b254c0a965025.hot-update.js",
    "/0.30d2bee02871731fa750.hot-update.js": "/0.30d2bee02871731fa750.hot-update.js",
    "/0.ee75fec6a4312c3ebade.hot-update.js": "/0.ee75fec6a4312c3ebade.hot-update.js",
    "/0.684af04f525fa6f27d48.hot-update.js": "/0.684af04f525fa6f27d48.hot-update.js",
    "/0.2674a6c5b6c4eea2ebae.hot-update.js": "/0.2674a6c5b6c4eea2ebae.hot-update.js",
    "/0.0514783c3b108d9b4912.hot-update.js": "/0.0514783c3b108d9b4912.hot-update.js",
    "/0.bec583b6165e569b3ae7.hot-update.js": "/0.bec583b6165e569b3ae7.hot-update.js",
    "/0.6937ff984737bac85d1a.hot-update.js": "/0.6937ff984737bac85d1a.hot-update.js",
    "/0.7e14567553083fb27d00.hot-update.js": "/0.7e14567553083fb27d00.hot-update.js",
    "/0.d6a1bab343b80da4a2f1.hot-update.js": "/0.d6a1bab343b80da4a2f1.hot-update.js",
    "/0.ccac8f5866d0a4ca299f.hot-update.js": "/0.ccac8f5866d0a4ca299f.hot-update.js",
    "/0.85bef86927f6729de873.hot-update.js": "/0.85bef86927f6729de873.hot-update.js",
    "/0.436c80b0bb102062eaf9.hot-update.js": "/0.436c80b0bb102062eaf9.hot-update.js",
    "/0.03fb76155bc798cf98d6.hot-update.js": "/0.03fb76155bc798cf98d6.hot-update.js",
    "/0.78c63c56460819fb14d0.hot-update.js": "/0.78c63c56460819fb14d0.hot-update.js",
    "/0.4e76d255c009de590821.hot-update.js": "/0.4e76d255c009de590821.hot-update.js",
    "/0.3db3a88a363dceb8d19a.hot-update.js": "/0.3db3a88a363dceb8d19a.hot-update.js",
    "/0.e30d76062178df40a0fa.hot-update.js": "/0.e30d76062178df40a0fa.hot-update.js",
    "/0.86999f14c7163e31b3ae.hot-update.js": "/0.86999f14c7163e31b3ae.hot-update.js",
    "/0.f81b4b1f4e5d21c45541.hot-update.js": "/0.f81b4b1f4e5d21c45541.hot-update.js",
    "/0.8c742d49896fd0a789a2.hot-update.js": "/0.8c742d49896fd0a789a2.hot-update.js",
    "/0.ee240a37a40bc53ab8cd.hot-update.js": "/0.ee240a37a40bc53ab8cd.hot-update.js",
    "/0.44e1a649f96df27d4b38.hot-update.js": "/0.44e1a649f96df27d4b38.hot-update.js",
    "/0.7069f703b105c469dd02.hot-update.js": "/0.7069f703b105c469dd02.hot-update.js",
    "/0.0e1707d51b39c86161fc.hot-update.js": "/0.0e1707d51b39c86161fc.hot-update.js",
    "/0.22f4558b17498f68da38.hot-update.js": "/0.22f4558b17498f68da38.hot-update.js",
    "/0.785c29d4ce78edb2a1c8.hot-update.js": "/0.785c29d4ce78edb2a1c8.hot-update.js",
    "/0.cc462ea195609e81b50a.hot-update.js": "/0.cc462ea195609e81b50a.hot-update.js",
    "/0.324b64cd93305a5e87a5.hot-update.js": "/0.324b64cd93305a5e87a5.hot-update.js",
    "/0.a360277ad6e50b6d22f7.hot-update.js": "/0.a360277ad6e50b6d22f7.hot-update.js",
    "/0.411b99bb14e2a066502a.hot-update.js": "/0.411b99bb14e2a066502a.hot-update.js",
    "/0.7a302c7f96a77eafd88b.hot-update.js": "/0.7a302c7f96a77eafd88b.hot-update.js",
    "/0.762da8cec26ba0daa5f2.hot-update.js": "/0.762da8cec26ba0daa5f2.hot-update.js",
    "/0.0de87d57b14b7adac7e4.hot-update.js": "/0.0de87d57b14b7adac7e4.hot-update.js",
    "/0.328308e6d376c7d77f1c.hot-update.js": "/0.328308e6d376c7d77f1c.hot-update.js",
    "/0.91c4c159e8cbc60f732c.hot-update.js": "/0.91c4c159e8cbc60f732c.hot-update.js",
    "/0.c8088d0958d1f10ad15f.hot-update.js": "/0.c8088d0958d1f10ad15f.hot-update.js",
    "/0.e2364d1b81ac8ea5e1f3.hot-update.js": "/0.e2364d1b81ac8ea5e1f3.hot-update.js",
    "/0.b0e34ed2bd99b858c11e.hot-update.js": "/0.b0e34ed2bd99b858c11e.hot-update.js",
    "/0.546e52080381edf11910.hot-update.js": "/0.546e52080381edf11910.hot-update.js",
    "/0.8c75531b1b0138e8b789.hot-update.js": "/0.8c75531b1b0138e8b789.hot-update.js",
    "/0.c4a003449817f6041f75.hot-update.js": "/0.c4a003449817f6041f75.hot-update.js",
    "/0.5ff0190f01ace6010e52.hot-update.js": "/0.5ff0190f01ace6010e52.hot-update.js",
    "/0.35be437e25ac2f90fd38.hot-update.js": "/0.35be437e25ac2f90fd38.hot-update.js",
    "/0.d831e3a0631401f00bad.hot-update.js": "/0.d831e3a0631401f00bad.hot-update.js",
    "/0.dcc8f3d7c3a198d6f836.hot-update.js": "/0.dcc8f3d7c3a198d6f836.hot-update.js",
    "/0.f88b2e329b10539059bd.hot-update.js": "/0.f88b2e329b10539059bd.hot-update.js",
    "/0.eaef4bff14c3607b52b5.hot-update.js": "/0.eaef4bff14c3607b52b5.hot-update.js",
    "/0.d6230ca67fbd15500404.hot-update.js": "/0.d6230ca67fbd15500404.hot-update.js",
    "/0.ffc5ac33bf22a98b49fa.hot-update.js": "/0.ffc5ac33bf22a98b49fa.hot-update.js",
    "/0.0421e124c96a0d4fb152.hot-update.js": "/0.0421e124c96a0d4fb152.hot-update.js",
    "/0.b780f24c5d707d96fc1d.hot-update.js": "/0.b780f24c5d707d96fc1d.hot-update.js",
    "/0.145eb5a35470281c3228.hot-update.js": "/0.145eb5a35470281c3228.hot-update.js",
    "/0.2475633fe7d9c5db11a0.hot-update.js": "/0.2475633fe7d9c5db11a0.hot-update.js",
    "/0.2091d573e46b51a283a4.hot-update.js": "/0.2091d573e46b51a283a4.hot-update.js",
    "/0.c1a2091b177b2b9d112c.hot-update.js": "/0.c1a2091b177b2b9d112c.hot-update.js",
    "/0.ec717dcceb360456b5d3.hot-update.js": "/0.ec717dcceb360456b5d3.hot-update.js",
    "/0.e161c666f6d3ee94da91.hot-update.js": "/0.e161c666f6d3ee94da91.hot-update.js",
    "/0.64248418d5763b43bc1b.hot-update.js": "/0.64248418d5763b43bc1b.hot-update.js",
    "/0.3556b691390864773793.hot-update.js": "/0.3556b691390864773793.hot-update.js",
    "/0.4c8b293a6efa1c06294a.hot-update.js": "/0.4c8b293a6efa1c06294a.hot-update.js",
    "/0.3263d03da0fcfa3f6669.hot-update.js": "/0.3263d03da0fcfa3f6669.hot-update.js",
    "/0.136254a2aad8e4755135.hot-update.js": "/0.136254a2aad8e4755135.hot-update.js",
    "/0.57b3491bd07ef0a25bbb.hot-update.js": "/0.57b3491bd07ef0a25bbb.hot-update.js",
    "/0.cdf49525c852e5e47825.hot-update.js": "/0.cdf49525c852e5e47825.hot-update.js",
    "/0.6292c6873582112dcce5.hot-update.js": "/0.6292c6873582112dcce5.hot-update.js",
    "/0.bd5f76da2b0ae1f1d497.hot-update.js": "/0.bd5f76da2b0ae1f1d497.hot-update.js",
    "/0.a2b51d1bbae926813d49.hot-update.js": "/0.a2b51d1bbae926813d49.hot-update.js",
    "/0.3064678f6334f42c2246.hot-update.js": "/0.3064678f6334f42c2246.hot-update.js",
    "/0.62ecb4af2db70dcffcc0.hot-update.js": "/0.62ecb4af2db70dcffcc0.hot-update.js",
    "/0.0d4244ad5126a56712d2.hot-update.js": "/0.0d4244ad5126a56712d2.hot-update.js",
    "/0.916a03adc9a7de9ed261.hot-update.js": "/0.916a03adc9a7de9ed261.hot-update.js",
    "/0.ea9307f17666a4945fe9.hot-update.js": "/0.ea9307f17666a4945fe9.hot-update.js",
    "/0.ba2e8988afe50ccb4bf8.hot-update.js": "/0.ba2e8988afe50ccb4bf8.hot-update.js",
    "/0.da6889f2a519ad3e9d4c.hot-update.js": "/0.da6889f2a519ad3e9d4c.hot-update.js",
    "/0.929e418099bde3e296cc.hot-update.js": "/0.929e418099bde3e296cc.hot-update.js",
    "/0.72a361269eee0997611f.hot-update.js": "/0.72a361269eee0997611f.hot-update.js",
    "/0.8dd76ba21919cd820fcc.hot-update.js": "/0.8dd76ba21919cd820fcc.hot-update.js",
    "/0.1b792aeb46c1f89d3b21.hot-update.js": "/0.1b792aeb46c1f89d3b21.hot-update.js",
    "/0.20be084202361e3c2a0d.hot-update.js": "/0.20be084202361e3c2a0d.hot-update.js",
    "/0.69e84e8f2a18fb662187.hot-update.js": "/0.69e84e8f2a18fb662187.hot-update.js",
    "/0.5ce081d1b29822f29d01.hot-update.js": "/0.5ce081d1b29822f29d01.hot-update.js",
    "/0.6d13ea75f04dead85d1a.hot-update.js": "/0.6d13ea75f04dead85d1a.hot-update.js",
    "/0.2f5857f0fd33bf72ceb5.hot-update.js": "/0.2f5857f0fd33bf72ceb5.hot-update.js",
    "/0.89e6e037bfa027845edd.hot-update.js": "/0.89e6e037bfa027845edd.hot-update.js",
    "/0.aebc2598fe646640f52a.hot-update.js": "/0.aebc2598fe646640f52a.hot-update.js",
    "/0.e99ba4ab19766064e462.hot-update.js": "/0.e99ba4ab19766064e462.hot-update.js",
    "/0.b99b475db5e517bc2c88.hot-update.js": "/0.b99b475db5e517bc2c88.hot-update.js",
    "/0.978e0862777ba35f2f24.hot-update.js": "/0.978e0862777ba35f2f24.hot-update.js",
    "/0.0a8f367518f5cc1205b8.hot-update.js": "/0.0a8f367518f5cc1205b8.hot-update.js",
    "/0.2f1217d4aa906063412c.hot-update.js": "/0.2f1217d4aa906063412c.hot-update.js",
    "/0.71c3d919f8b4071f71f8.hot-update.js": "/0.71c3d919f8b4071f71f8.hot-update.js",
    "/0.cddb0b7e7a1a6f955d46.hot-update.js": "/0.cddb0b7e7a1a6f955d46.hot-update.js",
    "/0.fdaf280e12ffe9292b8b.hot-update.js": "/0.fdaf280e12ffe9292b8b.hot-update.js",
    "/0.53349e5ec5a6730ff944.hot-update.js": "/0.53349e5ec5a6730ff944.hot-update.js",
    "/0.8d2dfe75f0023a040c6d.hot-update.js": "/0.8d2dfe75f0023a040c6d.hot-update.js",
    "/0.b90e45741e8fa7d6c455.hot-update.js": "/0.b90e45741e8fa7d6c455.hot-update.js",
    "/0.f552963121d955f23120.hot-update.js": "/0.f552963121d955f23120.hot-update.js",
    "/0.9c78a5861a2138cf4370.hot-update.js": "/0.9c78a5861a2138cf4370.hot-update.js",
    "/0.2599ab3c99812776b5ba.hot-update.js": "/0.2599ab3c99812776b5ba.hot-update.js",
    "/0.96d980093d0ef6456968.hot-update.js": "/0.96d980093d0ef6456968.hot-update.js",
    "/0.d9ac22c06ad2b9462caf.hot-update.js": "/0.d9ac22c06ad2b9462caf.hot-update.js",
    "/0.725d6f97af63e01258a8.hot-update.js": "/0.725d6f97af63e01258a8.hot-update.js",
    "/0.4ab5a489144321360a5e.hot-update.js": "/0.4ab5a489144321360a5e.hot-update.js",
    "/0.0c1bfda84ce58c98e0dc.hot-update.js": "/0.0c1bfda84ce58c98e0dc.hot-update.js",
    "/0.f5b68d3296f2639bc27b.hot-update.js": "/0.f5b68d3296f2639bc27b.hot-update.js",
    "/0.210f9a796815f552675c.hot-update.js": "/0.210f9a796815f552675c.hot-update.js",
    "/0.217e78959f034e8fb84d.hot-update.js": "/0.217e78959f034e8fb84d.hot-update.js",
    "/0.e8d3202f34d28a2ee53a.hot-update.js": "/0.e8d3202f34d28a2ee53a.hot-update.js",
    "/0.8f0e7fe7d2ce0ff50b63.hot-update.js": "/0.8f0e7fe7d2ce0ff50b63.hot-update.js",
    "/0.24eaaf11ddaff948b232.hot-update.js": "/0.24eaaf11ddaff948b232.hot-update.js",
    "/0.be2f0ba949a642912f8e.hot-update.js": "/0.be2f0ba949a642912f8e.hot-update.js",
    "/0.655b698af07a8dabdf96.hot-update.js": "/0.655b698af07a8dabdf96.hot-update.js",
    "/0.b59aa6b41cb5a80ef926.hot-update.js": "/0.b59aa6b41cb5a80ef926.hot-update.js",
    "/0.7ef05b0bef82380e81f2.hot-update.js": "/0.7ef05b0bef82380e81f2.hot-update.js",
    "/0.9ddaef22b71782fefb71.hot-update.js": "/0.9ddaef22b71782fefb71.hot-update.js",
    "/0.4c1ad9523ad1efb709ec.hot-update.js": "/0.4c1ad9523ad1efb709ec.hot-update.js",
    "/0.95ca6e674467a461870a.hot-update.js": "/0.95ca6e674467a461870a.hot-update.js",
    "/0.42f861ae73e668da906f.hot-update.js": "/0.42f861ae73e668da906f.hot-update.js",
    "/0.8abec6ac29f9efe3e97e.hot-update.js": "/0.8abec6ac29f9efe3e97e.hot-update.js",
    "/0.513ba97e62842c43856a.hot-update.js": "/0.513ba97e62842c43856a.hot-update.js",
    "/0.5410d330fecee0fe6584.hot-update.js": "/0.5410d330fecee0fe6584.hot-update.js",
    "/0.f531a9383337dff6dc85.hot-update.js": "/0.f531a9383337dff6dc85.hot-update.js",
    "/0.2936577300abaf49796a.hot-update.js": "/0.2936577300abaf49796a.hot-update.js",
    "/0.a2869d5bd7d35bae512c.hot-update.js": "/0.a2869d5bd7d35bae512c.hot-update.js",
    "/0.620e60faf095b96f2ca8.hot-update.js": "/0.620e60faf095b96f2ca8.hot-update.js",
    "/0.a369a47d1209bef4ac51.hot-update.js": "/0.a369a47d1209bef4ac51.hot-update.js",
    "/0.3a189c5b2104d5e271fa.hot-update.js": "/0.3a189c5b2104d5e271fa.hot-update.js",
    "/0.306c0bcd3ece23959ce7.hot-update.js": "/0.306c0bcd3ece23959ce7.hot-update.js",
    "/0.cd09f64ab45fde6fb558.hot-update.js": "/0.cd09f64ab45fde6fb558.hot-update.js",
    "/0.c610835d48913db2ef93.hot-update.js": "/0.c610835d48913db2ef93.hot-update.js",
    "/0.9be21061cdffbe00a1d4.hot-update.js": "/0.9be21061cdffbe00a1d4.hot-update.js",
    "/0.9cc05b2bdef1ff653047.hot-update.js": "/0.9cc05b2bdef1ff653047.hot-update.js",
    "/0.997c2923b6a3ae65b928.hot-update.js": "/0.997c2923b6a3ae65b928.hot-update.js",
    "/0.361a53c747391edb7b12.hot-update.js": "/0.361a53c747391edb7b12.hot-update.js",
    "/0.93e96c6ba4b1514092e2.hot-update.js": "/0.93e96c6ba4b1514092e2.hot-update.js",
    "/0.6a11f0d34e1e478c56b6.hot-update.js": "/0.6a11f0d34e1e478c56b6.hot-update.js",
    "/0.f05843636414ffeb225a.hot-update.js": "/0.f05843636414ffeb225a.hot-update.js",
    "/0.11f470278ed8582e5ef0.hot-update.js": "/0.11f470278ed8582e5ef0.hot-update.js",
    "/0.daa8c4579990bf7e8f43.hot-update.js": "/0.daa8c4579990bf7e8f43.hot-update.js",
    "/0.4c5333007e7014b3c6fe.hot-update.js": "/0.4c5333007e7014b3c6fe.hot-update.js",
    "/0.2cd7d1f8b1ad270362e3.hot-update.js": "/0.2cd7d1f8b1ad270362e3.hot-update.js",
    "/0.954cfdfcfd3d406fe1e7.hot-update.js": "/0.954cfdfcfd3d406fe1e7.hot-update.js",
    "/0.038d4a4600f7a9e45cc1.hot-update.js": "/0.038d4a4600f7a9e45cc1.hot-update.js",
    "/0.414d54b93bf7c0328768.hot-update.js": "/0.414d54b93bf7c0328768.hot-update.js",
    "/0.4caacdbfff7062b6e180.hot-update.js": "/0.4caacdbfff7062b6e180.hot-update.js",
    "/0.4eac9a7d39f4cb001dad.hot-update.js": "/0.4eac9a7d39f4cb001dad.hot-update.js",
    "/0.274caff554765441c802.hot-update.js": "/0.274caff554765441c802.hot-update.js",
    "/0.d74098dcbe530515554c.hot-update.js": "/0.d74098dcbe530515554c.hot-update.js",
    "/0.9aecb41a570c7c8c0201.hot-update.js": "/0.9aecb41a570c7c8c0201.hot-update.js",
    "/0.f541f0de31dc9786a746.hot-update.js": "/0.f541f0de31dc9786a746.hot-update.js",
    "/0.61ac7921e06f61f743c6.hot-update.js": "/0.61ac7921e06f61f743c6.hot-update.js",
    "/0.ac8fd7fbdfeffceeb42e.hot-update.js": "/0.ac8fd7fbdfeffceeb42e.hot-update.js",
    "/0.dd98712346a47fc2cb79.hot-update.js": "/0.dd98712346a47fc2cb79.hot-update.js",
    "/0.aee0701d3b895ae9cc9c.hot-update.js": "/0.aee0701d3b895ae9cc9c.hot-update.js",
    "/0.e278fbd87813b360e1b8.hot-update.js": "/0.e278fbd87813b360e1b8.hot-update.js",
    "/0.914c30c5dcb4c60b7c4b.hot-update.js": "/0.914c30c5dcb4c60b7c4b.hot-update.js",
    "/0.cd66243fb99677be12e0.hot-update.js": "/0.cd66243fb99677be12e0.hot-update.js",
    "/0.e351a76a709348b4d337.hot-update.js": "/0.e351a76a709348b4d337.hot-update.js",
    "/0.7edbaec94eb1cbcc709c.hot-update.js": "/0.7edbaec94eb1cbcc709c.hot-update.js",
    "/0.1ef0e1e25069c053a334.hot-update.js": "/0.1ef0e1e25069c053a334.hot-update.js",
    "/0.b2dc0698ea2bd348f387.hot-update.js": "/0.b2dc0698ea2bd348f387.hot-update.js",
    "/0.e329ab0f0b1f0f2338ee.hot-update.js": "/0.e329ab0f0b1f0f2338ee.hot-update.js",
    "/0.e0ded9ffd37a302dffa9.hot-update.js": "/0.e0ded9ffd37a302dffa9.hot-update.js",
    "/0.4b16fbd0029432ba2721.hot-update.js": "/0.4b16fbd0029432ba2721.hot-update.js",
    "/0.9d2756cb26037b89def5.hot-update.js": "/0.9d2756cb26037b89def5.hot-update.js",
    "/0.aeba2e9e31463a6c8794.hot-update.js": "/0.aeba2e9e31463a6c8794.hot-update.js",
    "/0.5d5e95e3ba9faf12cb8e.hot-update.js": "/0.5d5e95e3ba9faf12cb8e.hot-update.js",
    "/0.e50827cf06fe2e636999.hot-update.js": "/0.e50827cf06fe2e636999.hot-update.js",
    "/0.76f96695b6bbd5e6c9c6.hot-update.js": "/0.76f96695b6bbd5e6c9c6.hot-update.js",
    "/0.60e3900ca4c643f532c9.hot-update.js": "/0.60e3900ca4c643f532c9.hot-update.js",
    "/0.8422a34c0b703672a2b6.hot-update.js": "/0.8422a34c0b703672a2b6.hot-update.js",
    "/0.10e15583cc6ef4adc0ae.hot-update.js": "/0.10e15583cc6ef4adc0ae.hot-update.js",
    "/0.fc0ccfb7fe5b9e067421.hot-update.js": "/0.fc0ccfb7fe5b9e067421.hot-update.js",
    "/0.37f0633ed6ea8016b6f9.hot-update.js": "/0.37f0633ed6ea8016b6f9.hot-update.js",
    "/0.9a02da924e2321cf2a8b.hot-update.js": "/0.9a02da924e2321cf2a8b.hot-update.js",
    "/0.d154ca3113d9f79dfae6.hot-update.js": "/0.d154ca3113d9f79dfae6.hot-update.js",
    "/0.7aab43747a88a474cdc5.hot-update.js": "/0.7aab43747a88a474cdc5.hot-update.js",
    "/0.59180c2e9123b93cda25.hot-update.js": "/0.59180c2e9123b93cda25.hot-update.js",
    "/0.4bd9d6d6fc59a4dae679.hot-update.js": "/0.4bd9d6d6fc59a4dae679.hot-update.js",
    "/0.efde5941300c68f1ac07.hot-update.js": "/0.efde5941300c68f1ac07.hot-update.js",
    "/0.eddcb388711435a2e95a.hot-update.js": "/0.eddcb388711435a2e95a.hot-update.js",
    "/0.5ff408c5d40fe50df544.hot-update.js": "/0.5ff408c5d40fe50df544.hot-update.js",
    "/0.7a7897bd7488682dc460.hot-update.js": "/0.7a7897bd7488682dc460.hot-update.js",
    "/0.1a4d6c0e3dea3a379dfc.hot-update.js": "/0.1a4d6c0e3dea3a379dfc.hot-update.js",
    "/0.364d56005b3e48405cf2.hot-update.js": "/0.364d56005b3e48405cf2.hot-update.js",
    "/0.3d586e8dc674d50d8406.hot-update.js": "/0.3d586e8dc674d50d8406.hot-update.js",
    "/0.a9758c9a64e8d2c4b4ca.hot-update.js": "/0.a9758c9a64e8d2c4b4ca.hot-update.js",
    "/0.c0a04f1b75e2208f854b.hot-update.js": "/0.c0a04f1b75e2208f854b.hot-update.js",
    "/0.a41d3cf49fa1035f6767.hot-update.js": "/0.a41d3cf49fa1035f6767.hot-update.js",
    "/0.a8bc9c42b625ae0ddc66.hot-update.js": "/0.a8bc9c42b625ae0ddc66.hot-update.js",
    "/0.9482efed6b728bc1a616.hot-update.js": "/0.9482efed6b728bc1a616.hot-update.js",
    "/0.2490ad4e52fa830cdfbb.hot-update.js": "/0.2490ad4e52fa830cdfbb.hot-update.js",
    "/0.0be46d14063dffd6b6f9.hot-update.js": "/0.0be46d14063dffd6b6f9.hot-update.js",
    "/0.b97ca644d09a9003258d.hot-update.js": "/0.b97ca644d09a9003258d.hot-update.js",
    "/0.3f28ac5fe648aa1af106.hot-update.js": "/0.3f28ac5fe648aa1af106.hot-update.js",
    "/0.5534c485a1b240749579.hot-update.js": "/0.5534c485a1b240749579.hot-update.js",
    "/0.931e50f4aa91ab8c7bcc.hot-update.js": "/0.931e50f4aa91ab8c7bcc.hot-update.js",
    "/0.4dea73c1203f3a215ef6.hot-update.js": "/0.4dea73c1203f3a215ef6.hot-update.js",
    "/0.9a03bd8af58e84ccbb5e.hot-update.js": "/0.9a03bd8af58e84ccbb5e.hot-update.js",
    "/0.8434fbe7edf23c077806.hot-update.js": "/0.8434fbe7edf23c077806.hot-update.js",
    "/0.9898f25b4e84ffec6bc4.hot-update.js": "/0.9898f25b4e84ffec6bc4.hot-update.js",
    "/0.fb8fa13cd2ac711f1f9c.hot-update.js": "/0.fb8fa13cd2ac711f1f9c.hot-update.js",
    "/0.c33f4e20e8291a263adf.hot-update.js": "/0.c33f4e20e8291a263adf.hot-update.js",
    "/0.d964c6ead8bc42aaf4ee.hot-update.js": "/0.d964c6ead8bc42aaf4ee.hot-update.js",
    "/0.0c9f166364ef25fce22d.hot-update.js": "/0.0c9f166364ef25fce22d.hot-update.js",
    "/0.c1f0ba9e4d5e7cbe7643.hot-update.js": "/0.c1f0ba9e4d5e7cbe7643.hot-update.js",
    "/0.fe68359638532b05e75a.hot-update.js": "/0.fe68359638532b05e75a.hot-update.js",
    "/0.449035d254a2032b3eb3.hot-update.js": "/0.449035d254a2032b3eb3.hot-update.js",
    "/0.523ca9bfd9b4de761c4a.hot-update.js": "/0.523ca9bfd9b4de761c4a.hot-update.js",
    "/0.cd890da1c97ea81c62e6.hot-update.js": "/0.cd890da1c97ea81c62e6.hot-update.js",
    "/0.7068006579689c651d1e.hot-update.js": "/0.7068006579689c651d1e.hot-update.js",
    "/0.35336fdb2849dad5e922.hot-update.js": "/0.35336fdb2849dad5e922.hot-update.js",
    "/0.48029890893d9ad5125a.hot-update.js": "/0.48029890893d9ad5125a.hot-update.js",
    "/0.44707013268ab4331610.hot-update.js": "/0.44707013268ab4331610.hot-update.js",
    "/0.8754fb8350872a00aedc.hot-update.js": "/0.8754fb8350872a00aedc.hot-update.js",
    "/0.5ee36e75f27aaefef42d.hot-update.js": "/0.5ee36e75f27aaefef42d.hot-update.js",
    "/0.2a47a0b91e1d4c0f48ee.hot-update.js": "/0.2a47a0b91e1d4c0f48ee.hot-update.js",
    "/0.3021e749c130ebeeecc3.hot-update.js": "/0.3021e749c130ebeeecc3.hot-update.js",
    "/0.72cc9a173d33d17a5b40.hot-update.js": "/0.72cc9a173d33d17a5b40.hot-update.js",
    "/0.db2c29103f6c736a07a8.hot-update.js": "/0.db2c29103f6c736a07a8.hot-update.js",
    "/0.35f62b2c62a989442b08.hot-update.js": "/0.35f62b2c62a989442b08.hot-update.js",
    "/0.e6f38951e6a26dfdab3b.hot-update.js": "/0.e6f38951e6a26dfdab3b.hot-update.js",
    "/0.e9f8e8fe00de7a3beb88.hot-update.js": "/0.e9f8e8fe00de7a3beb88.hot-update.js",
    "/0.cbe9d2092d40bc448fcb.hot-update.js": "/0.cbe9d2092d40bc448fcb.hot-update.js",
    "/0.a00b2834d698e2bd07bb.hot-update.js": "/0.a00b2834d698e2bd07bb.hot-update.js",
    "/0.389714f58d889274f4cf.hot-update.js": "/0.389714f58d889274f4cf.hot-update.js",
    "/0.776ff9bda938155b040a.hot-update.js": "/0.776ff9bda938155b040a.hot-update.js",
    "/0.c1ebd7d9c6c5869798f8.hot-update.js": "/0.c1ebd7d9c6c5869798f8.hot-update.js",
    "/0.9b7491d26676191e453e.hot-update.js": "/0.9b7491d26676191e453e.hot-update.js",
    "/0.1a1fe019296b508be85e.hot-update.js": "/0.1a1fe019296b508be85e.hot-update.js",
    "/0.f68af1f9d6a69272292a.hot-update.js": "/0.f68af1f9d6a69272292a.hot-update.js",
    "/0.c11372b34c10c20b554a.hot-update.js": "/0.c11372b34c10c20b554a.hot-update.js",
    "/0.9c24924019668b4a9f5b.hot-update.js": "/0.9c24924019668b4a9f5b.hot-update.js",
    "/0.0764ff4d2fb7f8b93069.hot-update.js": "/0.0764ff4d2fb7f8b93069.hot-update.js",
    "/0.83507f9f28a1241e4330.hot-update.js": "/0.83507f9f28a1241e4330.hot-update.js",
    "/0.ea6a9d2971da78ab9b8e.hot-update.js": "/0.ea6a9d2971da78ab9b8e.hot-update.js",
    "/0.9e36ffbd050903a28a1d.hot-update.js": "/0.9e36ffbd050903a28a1d.hot-update.js",
    "/0.e49977594124389da295.hot-update.js": "/0.e49977594124389da295.hot-update.js",
    "/0.d5405a1f9f5d72f80db9.hot-update.js": "/0.d5405a1f9f5d72f80db9.hot-update.js",
    "/0.4c936251f0d04045e2bf.hot-update.js": "/0.4c936251f0d04045e2bf.hot-update.js",
    "/0.5eaf73b64d486658140e.hot-update.js": "/0.5eaf73b64d486658140e.hot-update.js",
    "/0.f88f1755df18402d0277.hot-update.js": "/0.f88f1755df18402d0277.hot-update.js",
    "/0.8c8a2313ecc62a79bde4.hot-update.js": "/0.8c8a2313ecc62a79bde4.hot-update.js",
    "/0.9f7a5fe6d295474ee1ee.hot-update.js": "/0.9f7a5fe6d295474ee1ee.hot-update.js",
    "/0.4eefa24714467a6ad496.hot-update.js": "/0.4eefa24714467a6ad496.hot-update.js",
    "/0.4e24ea22d52310b1c7ad.hot-update.js": "/0.4e24ea22d52310b1c7ad.hot-update.js",
    "/0.feb7fe3ac54602bb3bcf.hot-update.js": "/0.feb7fe3ac54602bb3bcf.hot-update.js",
    "/0.1299fac2b73f47dddd2f.hot-update.js": "/0.1299fac2b73f47dddd2f.hot-update.js",
    "/0.a554fa20864e54114646.hot-update.js": "/0.a554fa20864e54114646.hot-update.js",
    "/0.77a6d36a4faf85216085.hot-update.js": "/0.77a6d36a4faf85216085.hot-update.js",
    "/0.1c53e5cbab19880eef85.hot-update.js": "/0.1c53e5cbab19880eef85.hot-update.js",
    "/0.83923e99610407297366.hot-update.js": "/0.83923e99610407297366.hot-update.js",
    "/0.f3a04c3ad70aa9a2cd49.hot-update.js": "/0.f3a04c3ad70aa9a2cd49.hot-update.js",
    "/0.34c1bced10820e969fe0.hot-update.js": "/0.34c1bced10820e969fe0.hot-update.js",
    "/0.afb0e0a91a7474178fa3.hot-update.js": "/0.afb0e0a91a7474178fa3.hot-update.js",
    "/0.2bd53df12c635ff3aa09.hot-update.js": "/0.2bd53df12c635ff3aa09.hot-update.js",
    "/0.8fd9c1d0cba5a99199ed.hot-update.js": "/0.8fd9c1d0cba5a99199ed.hot-update.js",
    "/0.bc71d19b9d86de493c54.hot-update.js": "/0.bc71d19b9d86de493c54.hot-update.js",
    "/0.aa044f460bf411eda57b.hot-update.js": "/0.aa044f460bf411eda57b.hot-update.js",
    "/0.f133401dcac2cb3c608b.hot-update.js": "/0.f133401dcac2cb3c608b.hot-update.js",
    "/0.81921fad7b683013804a.hot-update.js": "/0.81921fad7b683013804a.hot-update.js",
    "/0.511822c656a173ae5b5a.hot-update.js": "/0.511822c656a173ae5b5a.hot-update.js",
    "/0.f018e93905622670966d.hot-update.js": "/0.f018e93905622670966d.hot-update.js",
    "/0.693f7acf9b55d6ee5784.hot-update.js": "/0.693f7acf9b55d6ee5784.hot-update.js",
    "/0.1b9d00873a77f9a12f82.hot-update.js": "/0.1b9d00873a77f9a12f82.hot-update.js",
    "/0.8b01293957cf7418c736.hot-update.js": "/0.8b01293957cf7418c736.hot-update.js"
}